locallab/__init__.py
locallab/config.py
locallab/model_manager.py
locallab/py.typed
locallab/server.py
locallab/cli/__init__.py
locallab/cli/chat.py
locallab/cli/config.py
locallab/cli/connection.py
locallab/cli/interactive.py
locallab/cli/models.py
locallab/cli/ui.py
locallab/core/__init__.py
locallab/core/app.py
locallab/core/minimal.py
locallab/logger/__init__.py
locallab/logger/logger.py
locallab/routes/__init__.py
locallab/routes/generate.py
locallab/routes/models.py
locallab/routes/system.py
locallab/ui/__init__.py
locallab/ui/banners.py
locallab/utils/__init__.py
locallab/utils/early_config.py
locallab/utils/huggingface_search.py
locallab/utils/model_cache.py
locallab/utils/networking.py
locallab/utils/progress.py
locallab/utils/system.py
locallab-0.11.3.dist-info/licenses/LICENSE
locallab-0.11.3.dist-info/METADATA
locallab-0.11.3.dist-info/WHEEL
locallab-0.11.3.dist-info/entry_points.txt
locallab-0.11.3.dist-info/top_level.txt
locallab-0.11.3.dist-info/RECORD
