Metadata-Version: 2.4
Name: locallab
Version: 0.11.3
Summary: LocalLab: A lightweight AI inference server for running LLMs locally or in Google Colab with a friendly API.
Home-page: https://github.com/UtkarshTheDev/LocalLab
Author: Utkarsh Tiwari
Author-email: utkarshweb2023@gmail.com
Classifier: Development Status :: 3 - Alpha
Classifier: Intended Audience :: Developers
Classifier: License :: OSI Approved :: Apache Software License
Classifier: Programming Language :: Python :: 3
Classifier: Programming Language :: Python :: 3.9
Classifier: Programming Language :: Python :: 3.10
Classifier: Programming Language :: Python :: 3.11
Classifier: Operating System :: Microsoft :: Windows
Classifier: Operating System :: POSIX :: Linux
Classifier: Operating System :: MacOS
Requires-Python: >=3.9
License-File: LICENSE
Requires-Dist: fastapi<1.0.0,>=0.95.0
Requires-Dist: uvicorn<1.0.0,>=0.21.1
Requires-Dist: pydantic<3.0.0,>=2.0.0
Requires-Dist: python-dotenv<1.0.0,>=0.21.0
Requires-Dist: python-multipart>=0.0.5
Requires-Dist: dataclasses-json<1.0.0,>=0.5.7
Requires-Dist: torch<3.0.0,>=2.0.0
Requires-Dist: transformers<5.0.0,>=4.49.0
Requires-Dist: accelerate<1.0.0,>=0.18.0
Requires-Dist: click<9.0.0,>=8.1.3
Requires-Dist: rich<14.0.0,>=13.3.4
Requires-Dist: pyngrok<7.0.0,>=6.0.0
Requires-Dist: requests<3.0.0,>=2.28.2
Requires-Dist: httpx>=0.24.0
Requires-Dist: colorama>=0.4.4
Requires-Dist: websockets>=10.0
Requires-Dist: psutil>=5.8.0
Requires-Dist: nest-asyncio>=1.5.1
Requires-Dist: fastapi-cache2>=0.2.1
Requires-Dist: huggingface_hub>=0.20.0
Requires-Dist: typing_extensions>=4.0.0
Requires-Dist: questionary>=1.10.0
Requires-Dist: bitsandbytes<1.0.0,>=0.38.0
Requires-Dist: llama-cpp-python<1.0.0,>=0.1.74
Requires-Dist: netifaces>=0.11.0
Requires-Dist: nvidia-ml-py3>=7.352.0
Requires-Dist: pynvml>=11.0.0
Provides-Extra: dev
Requires-Dist: pytest>=7.0.0; extra == "dev"
Requires-Dist: pytest-asyncio>=0.15.0; extra == "dev"
Requires-Dist: pytest-cov>=4.0.0; extra == "dev"
Dynamic: author
Dynamic: author-email
Dynamic: classifier
Dynamic: description
Dynamic: description-content-type
Dynamic: home-page
Dynamic: license-file
Dynamic: provides-extra
Dynamic: requires-dist
Dynamic: requires-python
Dynamic: summary
